Metadata-Version: 1.0
Name: uduak-distributions
Version: 0.3
Summary: Gaussian_distributions
Home-page: UNKNOWN
Author: uduak umanah
Author-email: uduakumanah10@gmail.com
License: UNKNOWN
Platform: UNKNOWN
